suinspy/__init__.py
suinspy/client.py
suinspy/type/objects.py
suinspy/utils/constants.py
suinspy/utils/parser.py
suinspy/utils/queries.py
suinspy-0.2.1.dist-info/WHEEL
suinspy-0.2.1.dist-info/METADATA
suinspy-0.2.1.dist-info/RECORD
