Metadata-Version: 2.1
Name: suinspy
Version: 0.2.1
Summary: Sui Name Service Python SDK Client
Author: andreidev1
Author-email: andreid.dev@gmail.com
Requires-Python: >=3.10,<4.0
Classifier: Programming Language :: Python :: 3
Classifier: Programming Language :: Python :: 3.10
Requires-Dist: pysui (>=0.35.0,<0.36.0)
Requires-Dist: requests (>=2.31.0,<3.0.0)
